[
{"name":"tests/float/tfloat1.nim c","category":"float","target":"c","action":"run","result":"reSuccess","expected":"","given":"","machine":"loongson-pc","commit":"26c5f97614d","branch":"lit-fix-objc-math"},
{"name":"tests/float/tfloat2.nim c","category":"float","target":"c","action":"run","result":"reSuccess","expected":"","given":"","machine":"loongson-pc","commit":"26c5f97614d","branch":"lit-fix-objc-math"},
{"name":"tests/float/tfloat3.nim c","category":"float","target":"c","action":"run","result":"reJoined","expected":"","given":"","machine":"loongson-pc","commit":"26c5f97614d","branch":"lit-fix-objc-math"},
{"name":"tests/float/tfloat4.nim c","category":"float","target":"c","action":"run","result":"reJoined","expected":"","given":"","machine":"loongson-pc","commit":"26c5f97614d","branch":"lit-fix-objc-math"},
{"name":"tests/float/tfloat5.nim c","category":"float","target":"c","action":"run","result":"reJoined","expected":"","given":"","machine":"loongson-pc","commit":"26c5f97614d","branch":"lit-fix-objc-math"},
{"name":"tests/float/tfloat7.nim c","category":"float","target":"c","action":"run","result":"reJoined","expected":"","given":"","machine":"loongson-pc","commit":"26c5f97614d","branch":"lit-fix-objc-math"},
{"name":"tests/float/tfloatmod.nim c","category":"float","target":"c","action":"run","result":"reSuccess","expected":"","given":"","machine":"loongson-pc","commit":"26c5f97614d","branch":"lit-fix-objc-math"},
{"name":"tests/float/tfloatmod.nim cpp","category":"float","target":"cpp","action":"run","result":"reSuccess","expected":"","given":"","machine":"loongson-pc","commit":"26c5f97614d","branch":"lit-fix-objc-math"},
{"name":"tests/float/tfloatmod.nim js","category":"float","target":"js","action":"run","result":"reSuccess","expected":"","given":"","machine":"loongson-pc","commit":"26c5f97614d","branch":"lit-fix-objc-math"},
{"name":"tests/float/tfloatnan.nim c","category":"float","target":"c","action":"run","result":"reJoined","expected":"","given":"","machine":"loongson-pc","commit":"26c5f97614d","branch":"lit-fix-objc-math"},
{"name":"tests/float/tfloatrange.nim c","category":"float","target":"c","action":"run","result":"reSuccess","expected":"","given":"","machine":"loongson-pc","commit":"26c5f97614d","branch":"lit-fix-objc-math"},
{"name":"tests/float/tfloats.nim c -d:nimPreviewFloatRoundtrip","category":"float","target":"c","action":"run","result":"reSuccess","expected":"","given":"","machine":"loongson-pc","commit":"26c5f97614d","branch":"lit-fix-objc-math"},
{"name":"tests/float/tfloats.nim cpp -d:nimPreviewFloatRoundtrip","category":"float","target":"cpp","action":"run","result":"reSuccess","expected":"","given":"","machine":"loongson-pc","commit":"26c5f97614d","branch":"lit-fix-objc-math"},
{"name":"tests/float/tfloats.nim js -d:nimPreviewFloatRoundtrip","category":"float","target":"js","action":"run","result":"reSuccess","expected":"","given":"","machine":"loongson-pc","commit":"26c5f97614d","branch":"lit-fix-objc-math"},
{"name":"tests/float/tfloats.nim c -u:nimPreviewFloatRoundtrip","category":"float","target":"c","action":"run","result":"reSuccess","expected":"","given":"","machine":"loongson-pc","commit":"26c5f97614d","branch":"lit-fix-objc-math"},
{"name":"tests/float/tfloats.nim cpp -u:nimPreviewFloatRoundtrip","category":"float","target":"cpp","action":"run","result":"reSuccess","expected":"","given":"","machine":"loongson-pc","commit":"26c5f97614d","branch":"lit-fix-objc-math"},
{"name":"tests/float/tfloats.nim js -u:nimPreviewFloatRoundtrip","category":"float","target":"js","action":"run","result":"reSuccess","expected":"","given":"","machine":"loongson-pc","commit":"26c5f97614d","branch":"lit-fix-objc-math"},
{"name":"tests/float/tissue5821.nim c","category":"float","target":"c","action":"run","result":"reJoined","expected":"","given":"","machine":"loongson-pc","commit":"26c5f97614d","branch":"lit-fix-objc-math"},
{"name":"tests/float/tlenientops.nim c","category":"float","target":"c","action":"run","result":"reJoined","expected":"","given":"","machine":"loongson-pc","commit":"26c5f97614d","branch":"lit-fix-objc-math"}]
